cuteci/__init__.py
cuteci/deploy_qt.py
cuteci/install-qt.qs
cuteci-1.2.0.dist-info/DESCRIPTION.rst
cuteci-1.2.0.dist-info/METADATA
cuteci-1.2.0.dist-info/RECORD
cuteci-1.2.0.dist-info/WHEEL
cuteci-1.2.0.dist-info/entry_points.txt
cuteci-1.2.0.dist-info/metadata.json
cuteci-1.2.0.dist-info/top_level.txt
cuteci-1.2.0.dist-info/zip-safe
