Metadata-Version: 2.0
Name: cuteci
Version: 1.2.0
Summary: CuteCI is a simple tool allowing you to install Qt with desired packages in headless mode.
Home-page: https://github.com/hasboeuf/cuteci
Author: Adrien Gavignet
Author-email: adrien.gavignet@gmail.com
License: MIT
Keywords: qt deploy install headless docker
Platform: UNKNOWN
Classifier: Programming Language :: Python :: 3
Classifier: License :: OSI Approved :: MIT License
Classifier: Operating System :: OS Independent
